rrlib.py
rrlib-0.1.0.dist-info/WHEEL
rrlib-0.1.0.dist-info/METADATA
rrlib-0.1.0.dist-info/RECORD
