Metadata-Version: 2.1
Name: rrlib
Version: 0.1.0
Summary: Chatbot request and response tool
Author: exerussus
Author-email: solovyov.production@gmail.com
Requires-Python: >=3.10,<4.0
Classifier: Programming Language :: Python :: 3
Classifier: Programming Language :: Python :: 3.10
